prompt_string/__init__.py
prompt_string/string.py
prompt_string/string_chain.py
prompt_string/token.py
prompt_string/types.py
prompt_string-0.0.1.dist-info/LICENSE
prompt_string-0.0.1.dist-info/METADATA
prompt_string-0.0.1.dist-info/WHEEL
prompt_string-0.0.1.dist-info/top_level.txt
prompt_string-0.0.1.dist-info/RECORD
