Metadata-Version: 2.1
Name: prompt-string
Version: 0.0.1
Summary: Treat prompt as a data type in Python
Home-page: https://github.com/memodb-io/prompt-string
Author: GusYe
Classifier: Programming Language :: Python :: 3
Classifier: License :: OSI Approved :: MIT License
Classifier: Operating System :: OS Independent
Requires-Python: >=3.11
License-File: LICENSE
Requires-Dist: tiktoken
